[
  {
    "name": "Mamta Kumari",
    "mobile_number": "9507715363.0",
    "assembly": "Lakhisarai"
  },
  {
    "name": "Sunil Ram",
    "mobile_number": "7320939575.0",
    "assembly": "Lakhisarai"
  },
  {
    "name": "Dinesh Chandravanshi",
    "mobile_number": "9031845336.0",
    "assembly": "Lakhisarai"
  },
  {
    "name": "Rajeev Kahar",
    "mobile_number": "9097447464.0",
    "assembly": "Lakhisarai"
  },
  {
    "name": "Jay prakash Gupta",
    "mobile_number": "9525777797.0",
    "assembly": "Lakhisarai"
  },
  {
    "name": "Sunil Gupta",
    "mobile_number": "7870221640.0",
    "assembly": "Lakhisarai"
  },
  {
    "name": "Babita Devi",
    "mobile_number": "9065787538.0",
    "assembly": "Lakhisarai"
  },
  {
    "name": "Akhilesh Yadav",
    "mobile_number": "9572397596.0",
    "assembly": "Lakhisarai"
  },
  {
    "name": "Uma Bharti",
    "mobile_number": "9006355200.0",
    "assembly": "Lakhisarai"
  },
  {
    "name": "Radha Kumari",
    "mobile_number": "9934038031.0",
    "assembly": "Lakhisarai"
  },
  {
    "name": "Rachit Ram",
    "mobile_number": "8084364396.0",
    "assembly": "Lakhisarai"
  },
  {
    "name": "Vasant Manjhi",
    "mobile_number": "8521959005.0",
    "assembly": "Lakhisarai"
  },
  {
    "name": "Manoj Ram",
    "mobile_number": "9576811510, 6203911406",
    "assembly": "Lakhisarai"
  },
  {
    "name": "Bambam Paswan",
    "mobile_number": "7004044848, 7633919829",
    "assembly": "Lakhisarai"
  },
  {
    "name": "Ram kumar Paswan",
    "mobile_number": "6203281834.0",
    "assembly": "Lakhisarai"
  },
  {
    "name": "Rekha Devi",
    "mobile_number": "8292547763.0",
    "assembly": "Lakhisarai"
  },
  {
    "name": "Vishakha Kumari",
    "mobile_number": "9031366194.0",
    "assembly": "Lakhisarai"
  },
  {
    "name": "Ganga Rajak",
    "mobile_number": "7970406319.0",
    "assembly": "Lakhisarai"
  },
  {
    "name": "Harish Kumar Pandey",
    "mobile_number": "9097369597.0",
    "assembly": "Lakhisarai"
  },
  {
    "name": "Naval Ram",
    "mobile_number": "7549954288.0",
    "assembly": "Lakhisarai"
  },
  {
    "name": "Md. Waris",
    "mobile_number": "9504044988.0",
    "assembly": "Lakhisarai"
  },
  {
    "name": "Vikas Sahu",
    "mobile_number": "7488799643.0",
    "assembly": "Lakhisarai"
  },
  {
    "name": "Pintu Thakur",
    "mobile_number": "6204476435.0",
    "assembly": "Lakhisarai"
  },
  {
    "name": "Arvind Yadav",
    "mobile_number": "8804953630.0",
    "assembly": "Lakhisarai"
  },
  {
    "name": "Anandi Bind",
    "mobile_number": "8603064834.0",
    "assembly": "Lakhisarai"
  },
  {
    "name": "Dayanand Yadav",
    "mobile_number": "8969915789.0",
    "assembly": "Lakhisarai"
  },
  {
    "name": "Raana Yadav",
    "mobile_number": "8210611872.0",
    "assembly": "Lakhisarai"
  },
  {
    "name": "ShivNandan Mahto",
    "mobile_number": "9852567270.0",
    "assembly": "Lakhisarai"
  },
  {
    "name": "Annapurna Devi",
    "mobile_number": "7061618704.0",
    "assembly": "Lakhisarai"
  },
  {
    "name": "Pankaj Kumar Verma",
    "mobile_number": "9472226808.0",
    "assembly": "Lakhisarai"
  },
  {
    "name": "Sarita Devi",
    "mobile_number": "8340599978.0",
    "assembly": "Lakhisarai"
  },
  {
    "name": "Choti Khatton",
    "mobile_number": "6205369824.0",
    "assembly": "Lakhisarai"
  },
  {
    "name": "Roshan Khatoon",
    "mobile_number": "8252208657.0",
    "assembly": "Lakhisarai"
  },
  {
    "name": "Kameshwar Manjhi",
    "mobile_number": "8210916152.0",
    "assembly": "Lakhisarai"
  },
  {
    "name": "Ajay Yadav",
    "mobile_number": "6207116440.0",
    "assembly": "Lakhisarai"
  },
  {
    "name": "Neeraj mandal",
    "mobile_number": "8581894200.0",
    "assembly": "Lakhisarai"
  },
  {
    "name": "Vikas Kumar",
    "mobile_number": "8252112419.0",
    "assembly": "Lakhisarai"
  },
  {
    "name": "Vibha mahto",
    "mobile_number": "7903452403.0",
    "assembly": "Lakhisarai"
  },
  {
    "name": "Hemant mahto",
    "mobile_number": "9631024249.0",
    "assembly": "Lakhisarai"
  },
  {
    "name": "Babita Devi",
    "mobile_number": "7061882848.0",
    "assembly": "Lakhisarai"
  },
  {
    "name": "Md Izhar alam",
    "mobile_number": "9122204490.0",
    "assembly": "Lakhisarai"
  },
  {
    "name": "Ashok Ram",
    "mobile_number": "9801448859.0",
    "assembly": "Lakhisarai"
  },
  {
    "name": "Hakim Paswan",
    "mobile_number": "9431081394.0",
    "assembly": "Lakhisarai"
  },
  {
    "name": "Parmanand Mandal",
    "mobile_number": "8002956356.0",
    "assembly": "Lakhisarai"
  },
  {
    "name": "Prabhat kumar",
    "mobile_number": "7277169850.0",
    "assembly": "Lakhisarai"
  },
  {
    "name": "Pawan Sahni",
    "mobile_number": "8083230955, 7258876192",
    "assembly": "Lakhisarai"
  },
  {
    "name": "Satrudhan Singh",
    "mobile_number": "9504045039.0",
    "assembly": "Lakhisarai"
  },
  {
    "name": "Loha singh",
    "mobile_number": "9835476062.0",
    "assembly": "Lakhisarai"
  },
  {
    "name": "Jyoti Thakur",
    "mobile_number": "9877964534.0",
    "assembly": "Lakhisarai"
  },
  {
    "name": "Ram Pravesh kumar Yadav",
    "mobile_number": "6203819093.0",
    "assembly": "Lakhisarai"
  },
  {
    "name": "Pramod Malik",
    "mobile_number": "7479771151.0",
    "assembly": "Lakhisarai"
  },
  {
    "name": "Sachin kumar",
    "mobile_number": "9304074624.0",
    "assembly": "Lakhisarai"
  },
  {
    "name": "Rahul Mahto",
    "mobile_number": "7277643554.0",
    "assembly": "Lakhisarai"
  },
  {
    "name": "Mahesh Singh",
    "mobile_number": "9931895963.0",
    "assembly": "Lakhisarai"
  },
  {
    "name": "Ajay Kumar Singh",
    "mobile_number": "9973539669.0",
    "assembly": "Lakhisarai"
  },
  {
    "name": "ASHISH PASWAN",
    "mobile_number": "8102218267.0",
    "assembly": "Lakhisarai"
  },
  {
    "name": "SUNNY PASWAN",
    "mobile_number": "6205236661.0",
    "assembly": "Lakhisarai"
  },
  {
    "name": "Sunil kumar",
    "mobile_number": "9709761432.0",
    "assembly": "Lakhisarai"
  },
  {
    "name": "Abhay Kumar singh - Sonu",
    "mobile_number": "9431257212.0",
    "assembly": "Lakhisarai"
  },
  {
    "name": "Manoj bharti",
    "mobile_number": "9006738320.0",
    "assembly": "Lakhisarai"
  },
  {
    "name": "Uchit Yadav",
    "mobile_number": "8292293427.0",
    "assembly": "Lakhisarai"
  },
  {
    "name": "Asgar Shah",
    "mobile_number": "7739103247.0",
    "assembly": "Lakhisarai"
  },
  {
    "name": "Rampravesh Paswan",
    "mobile_number": "9939355543.0",
    "assembly": "Lakhisarai"
  },
  {
    "name": "Sanjay Yadav",
    "mobile_number": "9123136364.0",
    "assembly": "Lakhisarai"
  },
  {
    "name": "Mamta Mahto",
    "mobile_number": "6204018202.0",
    "assembly": "Lakhisarai"
  },
  {
    "name": "Hariom Kumar",
    "mobile_number": "7050720310.0",
    "assembly": "Harlakhi"
  },
  {
    "name": "Bhavem Kumar Mahto",
    "mobile_number": "7050499388.0",
    "assembly": "Harlakhi"
  },
  {
    "name": "Jyoti Kumari",
    "mobile_number": "6200854663.0",
    "assembly": "Harlakhi"
  },
  {
    "name": "Ramam Spasht",
    "mobile_number": "8298179247.0",
    "assembly": "Harlakhi"
  },
  {
    "name": "Anjali Kumari",
    "mobile_number": "8340248951.0",
    "assembly": "Harlakhi"
  },
  {
    "name": "Gokulanand Jhap",
    "mobile_number": "7260869523.0",
    "assembly": "Harlakhi"
  },
  {
    "name": "Subhash Yadav",
    "mobile_number": "7488340121.0",
    "assembly": "Harlakhi"
  },
  {
    "name": "Vivek Kumar Mahto",
    "mobile_number": "9661084733.0",
    "assembly": "Harlakhi"
  },
  {
    "name": "Anjali Kumari",
    "mobile_number": "6201897459.0",
    "assembly": "Harlakhi"
  },
  {
    "name": "Sitesh Kumar Paswan",
    "mobile_number": "9631275390.0",
    "assembly": "Harlakhi"
  },
  {
    "name": "Govind Mahto",
    "mobile_number": "9973734918.0",
    "assembly": "Harlakhi"
  },
  {
    "name": "Naresh Shah",
    "mobile_number": "8084651416.0",
    "assembly": "Harlakhi"
  },
  {
    "name": "Md Sohail",
    "mobile_number": "7764079174.0",
    "assembly": "Harlakhi"
  },
  {
    "name": "Mohammad Shafique",
    "mobile_number": "9871828656.0",
    "assembly": "Harlakhi"
  },
  {
    "name": "Naresh",
    "mobile_number": "7070832712.0",
    "assembly": "Harlakhi"
  },
  {
    "name": "Ishwar Dayal",
    "mobile_number": "8757711231.0",
    "assembly": "Wazirganj"
  },
  {
    "name": "Ranjeet Kumar",
    "mobile_number": "7857823003.0",
    "assembly": "Wazirganj"
  },
  {
    "name": "Vikram Kumar",
    "mobile_number": "9955738758.0",
    "assembly": "Wazirganj"
  },
  {
    "name": "Deepak Kumar",
    "mobile_number": "766764867.0",
    "assembly": "Wazirganj"
  },
  {
    "name": "Shiv Shankar",
    "mobile_number": "6202559388.0",
    "assembly": "Wazirganj"
  },
  {
    "name": "Praveen Kumar",
    "mobile_number": "9690245343.0",
    "assembly": "Wazirganj"
  },
  {
    "name": "Mohit Kumar",
    "mobile_number": "9693505248.0",
    "assembly": "Wazirganj"
  },
  {
    "name": "Sanjay Kumar",
    "mobile_number": "9471839543.0",
    "assembly": "Wazirganj"
  },
  {
    "name": "Dhirendar Kumar",
    "mobile_number": "9097018111.0",
    "assembly": "Wazirganj"
  },
  {
    "name": "Chhotu Kumar",
    "mobile_number": "8229059662.0",
    "assembly": "Wazirganj"
  },
  {
    "name": "Raushan Kumar",
    "mobile_number": "8757014710.0",
    "assembly": "Wazirganj"
  },
  {
    "name": "Dindayal Kumar",
    "mobile_number": "9304531815.0",
    "assembly": "Wazirganj"
  },
  {
    "name": "Ajay Kumar",
    "mobile_number": "8709839243.0",
    "assembly": "Wazirganj"
  },
  {
    "name": "Sujit Kumar",
    "mobile_number": "9142773498.0",
    "assembly": "Wazirganj"
  },
  {
    "name": "Vinay Kumar",
    "mobile_number": "9708837524.0",
    "assembly": "Wazirganj"
  },
  {
    "name": "Ravi Kumar",
    "mobile_number": "7903413989.0",
    "assembly": "Wazirganj"
  },
  {
    "name": "Nagendra Kumar",
    "mobile_number": "9155758492.0",
    "assembly": "Wazirganj"
  },
  {
    "name": "Vikash Kumar",
    "mobile_number": "7739730459.0",
    "assembly": "Wazirganj"
  },
  {
    "name": "Akash Kumar",
    "mobile_number": "7903009934.0",
    "assembly": "Wazirganj"
  },
  {
    "name": "Rajeev Kumar",
    "mobile_number": "9262260506.0",
    "assembly": "Wazirganj"
  },
  {
    "name": "Vishal Kumar",
    "mobile_number": "8630180486.0",
    "assembly": "Wazirganj"
  },
  {
    "name": "Rahul Kumar",
    "mobile_number": "6204314090.0",
    "assembly": "Wazirganj"
  },
  {
    "name": "Subhash Kumar",
    "mobile_number": "9155981546.0",
    "assembly": "Wazirganj"
  },
  {
    "name": "Manish Kumar",
    "mobile_number": "8084180991.0",
    "assembly": "Wazirganj"
  },
  {
    "name": "Pankaj Kumar",
    "mobile_number": "9504602272.0",
    "assembly": "Wazirganj"
  },
  {
    "name": "Nitish Kumar",
    "mobile_number": "6209661405.0",
    "assembly": "Wazirganj"
  },
  {
    "name": "Abhay Kumar",
    "mobile_number": "9931059565.0",
    "assembly": "Harnaut"
  },
  {
    "name": "Dinesh Jamadar",
    "mobile_number": "7633948045.0",
    "assembly": "Harnaut"
  },
  {
    "name": "Bacchan Kumar",
    "mobile_number": "7765846551.0",
    "assembly": "Harnaut"
  },
  {
    "name": "Suhani Sinha",
    "mobile_number": "9905487919.0",
    "assembly": "Harnaut"
  },
  {
    "name": "Sunita Devi",
    "mobile_number": "8002370889.0",
    "assembly": "Harnaut"
  },
  {
    "name": "Jai Prakash Kumar",
    "mobile_number": "9570464752.0",
    "assembly": "Harnaut"
  },
  {
    "name": "Anjani Kumar",
    "mobile_number": "8969864115.0",
    "assembly": "Harnaut"
  },
  {
    "name": "Ajit Kumar Ram",
    "mobile_number": "9934272087.0",
    "assembly": "Harnaut"
  },
  {
    "name": "Urmila Devi",
    "mobile_number": "8735979323.0",
    "assembly": "Harnaut"
  },
  {
    "name": "Sanoj Kumar",
    "mobile_number": "9525146391.0",
    "assembly": "Harnaut"
  },
  {
    "name": "Sarita Devi",
    "mobile_number": "7549289551.0",
    "assembly": "Harnaut"
  },
  {
    "name": "Ramuchit Jamadar",
    "mobile_number": "6209662976.0",
    "assembly": "Harnaut"
  },
  {
    "name": "Satyendra Prasad",
    "mobile_number": "9006891188.0",
    "assembly": "Harnaut"
  },
  {
    "name": "Seema Devi",
    "mobile_number": "6299648310.0",
    "assembly": "Harnaut"
  },
  {
    "name": "Snehlata Kumari",
    "mobile_number": "7004834266.0",
    "assembly": "Harnaut"
  },
  {
    "name": "Usha Devi",
    "mobile_number": "6207400315.0",
    "assembly": "Harnaut"
  },
  {
    "name": "Ganga Vishun Jamadar",
    "mobile_number": "7808261928.0",
    "assembly": "Harnaut"
  },
  {
    "name": "Raushan Kumar",
    "mobile_number": "9771401335.0",
    "assembly": "Harnaut"
  },
  {
    "name": "Kiran Devi",
    "mobile_number": "9835325070.0",
    "assembly": "Harnaut"
  },
  {
    "name": "Jayant Kumar Singh",
    "mobile_number": "9693167773.0",
    "assembly": "Harnaut"
  },
  {
    "name": "Sunita Devi",
    "mobile_number": "9128284927.0",
    "assembly": "Harnaut"
  },
  {
    "name": "Aarti Kumari",
    "mobile_number": "6201871460.0",
    "assembly": "Harnaut"
  },
  {
    "name": "Manti Devi",
    "mobile_number": "8809420961.0",
    "assembly": "Harnaut"
  },
  {
    "name": "Shiv Mistri",
    "mobile_number": "8298619559.0",
    "assembly": "Harnaut"
  },
  {
    "name": "Deenanath Kumar",
    "mobile_number": "8789226099.0",
    "assembly": "Harnaut"
  },
  {
    "name": "Ajay Kumar",
    "mobile_number": "8804532173.0",
    "assembly": "Harnaut"
  },
  {
    "name": "Soni Devi",
    "mobile_number": "8002438548.0",
    "assembly": "Harnaut"
  },
  {
    "name": "Shri Ram Paswan",
    "mobile_number": "8757473940.0",
    "assembly": "Harnaut"
  },
  {
    "name": "Mamta Devi",
    "mobile_number": "8292213428.0",
    "assembly": "Harnaut"
  },
  {
    "name": "Amrita Devi",
    "mobile_number": "8294235217.0",
    "assembly": "Harnaut"
  },
  {
    "name": "Vipin Kumar",
    "mobile_number": "9162243414.0",
    "assembly": "Harnaut"
  },
  {
    "name": "Kumari Nibha Sinha",
    "mobile_number": "6203312040.0",
    "assembly": "Harnaut"
  },
  {
    "name": "Reena Devi",
    "mobile_number": "7352752311.0",
    "assembly": "Harnaut"
  },
  {
    "name": "Kiran Devi",
    "mobile_number": "9631226508.0",
    "assembly": "Harnaut"
  },
  {
    "name": "Sudhir Vind",
    "mobile_number": "9523487308.0",
    "assembly": "Harnaut"
  },
  {
    "name": "Pramila Devi",
    "mobile_number": "7870392175.0",
    "assembly": "Harnaut"
  },
  {
    "name": "Ram Charan Paswan",
    "mobile_number": "7563054235.0",
    "assembly": "Harnaut"
  },
  {
    "name": "Nitish Kumar",
    "mobile_number": "7004656149.0",
    "assembly": "Harnaut"
  },
  {
    "name": "Niru Devi",
    "mobile_number": "6207258153.0",
    "assembly": "Harnaut"
  },
  {
    "name": "Anita Devi",
    "mobile_number": "9162095813.0",
    "assembly": "Harnaut"
  },
  {
    "name": "Sita Devi",
    "mobile_number": "9931909862.0",
    "assembly": "Harnaut"
  },
  {
    "name": "Sohgiya Devi",
    "mobile_number": "9065679015.0",
    "assembly": "Harnaut"
  },
  {
    "name": "Shailesh Kumar",
    "mobile_number": "7654708253.0",
    "assembly": "Harnaut"
  },
  {
    "name": "Saroj Devi",
    "mobile_number": "9117438796.0",
    "assembly": "Harnaut"
  },
  {
    "name": "Siyawati Devi",
    "mobile_number": "9631510579.0",
    "assembly": "Harnaut"
  },
  {
    "name": "Manoj Singh",
    "mobile_number": "8102580521.0",
    "assembly": "Harnaut"
  },
  {
    "name": "Arvind Paswan",
    "mobile_number": "8490999275.0",
    "assembly": "Harnaut"
  },
  {
    "name": "Muskan Kumari",
    "mobile_number": "7294963913.0",
    "assembly": "Harnaut"
  },
  {
    "name": "Poonam Devi",
    "mobile_number": "9304989340.0",
    "assembly": "Harnaut"
  },
  {
    "name": "Geeta Devi",
    "mobile_number": "9315052778.0",
    "assembly": "Harnaut"
  },
  {
    "name": "Arun Malakar",
    "mobile_number": "9931815900.0",
    "assembly": "Harnaut"
  },
  {
    "name": "Rita Devi",
    "mobile_number": "6200549536.0",
    "assembly": "Harnaut"
  },
  {
    "name": "Gautam Kumar",
    "mobile_number": "9955579813.0",
    "assembly": "Harnaut"
  },
  {
    "name": "Raveena Devi",
    "mobile_number": "9155787414.0",
    "assembly": "Harnaut"
  },
  {
    "name": "Abhishek Kumar",
    "mobile_number": "9798588887.0",
    "assembly": "Harnaut"
  },
  {
    "name": "Jaymanti Kumari",
    "mobile_number": "9199928159.0",
    "assembly": "Harnaut"
  },
  {
    "name": "Shivji Prasad",
    "mobile_number": "6287880559.0",
    "assembly": "Harnaut"
  },
  {
    "name": "Suvili Devi",
    "mobile_number": "7091498973.0",
    "assembly": "Harnaut"
  },
  {
    "name": "Shrikant Paswan",
    "mobile_number": "7091445796.0",
    "assembly": "Harnaut"
  },
  {
    "name": "Anuja Kumari",
    "mobile_number": "7903156069.0",
    "assembly": "Harnaut"
  },
  {
    "name": "Amarnaath",
    "mobile_number": "7549440176.0",
    "assembly": "Harnaut"
  },
  {
    "name": "Umesh Prasad",
    "mobile_number": "7209436510.0",
    "assembly": "Harnaut"
  },
  {
    "name": "Pushpa Kumari",
    "mobile_number": "9835890832.0",
    "assembly": "Harnaut"
  },
  {
    "name": "Anirudh prasad",
    "mobile_number": "9973604662.0",
    "assembly": "Harnaut"
  },
  {
    "name": "Santosh kumar",
    "mobile_number": "9264282935.0",
    "assembly": "Harnaut"
  },
  {
    "name": "Rajendra Singh",
    "mobile_number": "9955822967.0",
    "assembly": "Harnaut"
  },
  {
    "name": "Naval Kishor Prasad",
    "mobile_number": "7766059441.0",
    "assembly": "Harnaut"
  },
  {
    "name": "Ranjeet Chauhan",
    "mobile_number": "6200476162.0",
    "assembly": "Harnaut"
  },
  {
    "name": "Sonu Chauhan",
    "mobile_number": "9162130537.0",
    "assembly": "Harnaut"
  },
  {
    "name": "Faujdari singh",
    "mobile_number": "9546514568.0",
    "assembly": "Harnaut"
  },
  {
    "name": "Indal prasad",
    "mobile_number": "9572610439.0",
    "assembly": "Harnaut"
  },
  {
    "name": "kameshwar prasad",
    "mobile_number": "7562933537.0",
    "assembly": "Harnaut"
  },
  {
    "name": "Narendra Sahi",
    "mobile_number": "7667871207.0",
    "assembly": "Harnaut"
  },
  {
    "name": "nawal yadav",
    "mobile_number": "9334243005.0",
    "assembly": "Harnaut"
  },
  {
    "name": "Rajesh chauhan",
    "mobile_number": "9798199319.0",
    "assembly": "Harnaut"
  },
  {
    "name": "mirdila kumari",
    "mobile_number": "8969335070.0",
    "assembly": "Harnaut"
  },
  {
    "name": "Subodh Kumar",
    "mobile_number": "7091332065.0",
    "assembly": "Arwal"
  },
  {
    "name": "Rajkumar",
    "mobile_number": "7488751378.0",
    "assembly": "Arwal"
  },
  {
    "name": "Ujjwal Kumar",
    "mobile_number": "8873613785.0",
    "assembly": "Arwal"
  },
  {
    "name": "Arjun Singh",
    "mobile_number": "9631229048.0",
    "assembly": "Arwal"
  },
  {
    "name": "Sikandar Kumar",
    "mobile_number": "7033959812.0",
    "assembly": "Arwal"
  },
  {
    "name": "Pappu Kumar",
    "mobile_number": "8757752901.0",
    "assembly": "Arwal"
  },
  {
    "name": "Sanjay Kumar",
    "mobile_number": "7484042954.0",
    "assembly": "Arwal"
  },
  {
    "name": "Pramila Kumari",
    "mobile_number": "9835600213.0",
    "assembly": "Arwal"
  },
  {
    "name": "Indu Kumari",
    "mobile_number": "9504143372.0",
    "assembly": "Arwal"
  },
  {
    "name": "Akshay Kumar",
    "mobile_number": "6206365883.0",
    "assembly": "Arwal"
  },
  {
    "name": "Vikas Kumar",
    "mobile_number": "9508083254.0",
    "assembly": "Arwal"
  },
  {
    "name": "Abhimanyu Kumar (Dr)",
    "mobile_number": "8002066561.0",
    "assembly": "Arwal"
  },
  {
    "name": "Amarendra Kumar",
    "mobile_number": "6204318716.0",
    "assembly": "Arwal"
  },
  {
    "name": "Satyendra Bind",
    "mobile_number": "8294945134.0",
    "assembly": "Arwal"
  },
  {
    "name": "Surendra Yadav",
    "mobile_number": "9771000297.0",
    "assembly": "Arwal"
  },
  {
    "name": "Ajay Yadav",
    "mobile_number": "8294946091.0",
    "assembly": "Arwal"
  },
  {
    "name": "Ramesh Kumar",
    "mobile_number": "9534652604.0",
    "assembly": "Arwal"
  },
  {
    "name": "Ranjit Kumar",
    "mobile_number": "9102776486.0",
    "assembly": "Arwal"
  },
  {
    "name": "Sunil Ram",
    "mobile_number": "7061992430.0",
    "assembly": "Arwal"
  },
  {
    "name": "Pintu Kumar",
    "mobile_number": "8310324048.0",
    "assembly": "Arwal"
  },
  {
    "name": "Ram Bihari Yadav",
    "mobile_number": "7257812106.0",
    "assembly": "Arwal"
  },
  {
    "name": "Manoj Kumar",
    "mobile_number": "7762887398.0",
    "assembly": "Arwal"
  },
  {
    "name": "Bachchan Rajvanshi",
    "mobile_number": "8298775638.0",
    "assembly": "Arwal"
  },
  {
    "name": "Sanjeet Kumar (Chainpur)",
    "mobile_number": "6203893706.0",
    "assembly": "Arwal"
  },
  {
    "name": "Nitish Kumar",
    "mobile_number": "9065585658.0",
    "assembly": "Arwal"
  },
  {
    "name": "Vikas Kumar",
    "mobile_number": "7543966608.0",
    "assembly": "Arwal"
  },
  {
    "name": "Arvind Kumar",
    "mobile_number": "8340511206.0",
    "assembly": "Arwal"
  },
  {
    "name": "Pintu Kumar",
    "mobile_number": "8797564240.0",
    "assembly": "Arwal"
  },
  {
    "name": "Ajit Kumar",
    "mobile_number": "8804190210.0",
    "assembly": "Arwal"
  },
  {
    "name": "Ramashankar Kumar",
    "mobile_number": "9199540939.0",
    "assembly": "Arwal"
  },
  {
    "name": "Ravi Shankar Kumar",
    "mobile_number": "6207930631.0",
    "assembly": "Arwal"
  },
  {
    "name": "Pappu Kumar",
    "mobile_number": "6207930631.0",
    "assembly": "Arwal"
  },
  {
    "name": "Anil Kumar",
    "mobile_number": "7654158771.0",
    "assembly": "Arwal"
  },
  {
    "name": "Gautam Kumar",
    "mobile_number": "9065589656.0",
    "assembly": "Arwal"
  },
  {
    "name": "Arvind Kumari (Shri Ram Bigha)",
    "mobile_number": "8905077729.0",
    "assembly": "Arwal"
  },
  {
    "name": "Manoj Kumar",
    "mobile_number": "9525781036.0",
    "assembly": "Arwal"
  },
  {
    "name": "Anil Kumar",
    "mobile_number": "8873195113.0",
    "assembly": "Arwal"
  },
  {
    "name": "Ram Ji Rajvanshi",
    "mobile_number": "9973524417.0",
    "assembly": "Arwal"
  },
  {
    "name": "Ghanshyam Sah",
    "mobile_number": "7782069133.0",
    "assembly": "Arwal"
  },
  {
    "name": "Rishikesh Kumar (Teacher)",
    "mobile_number": "9955.0",
    "assembly": "Arwal"
  },
  {
    "name": "Sanjeet Kumar",
    "mobile_number": "7939896002.0",
    "assembly": "Arwal"
  },
  {
    "name": "Prince Kumar",
    "mobile_number": "7319960500.0",
    "assembly": "Tikari"
  },
  {
    "name": "Ritish Kumar",
    "mobile_number": "9798263918.0",
    "assembly": "Tikari"
  },
  {
    "name": "Pritam Kumar",
    "mobile_number": "9097937103.0",
    "assembly": "Tikari"
  },
  {
    "name": "Barjesh Kumar",
    "mobile_number": "9060365941.0",
    "assembly": "Tikari"
  },
  {
    "name": "Jitendra Kumar",
    "mobile_number": "6203490074.0",
    "assembly": "Tikari"
  },
  {
    "name": "Omprey Yadav",
    "mobile_number": "9631649075.0",
    "assembly": "Tikari"
  },
  {
    "name": "Rubi Devi",
    "mobile_number": "9608783425.0",
    "assembly": "Tikari"
  },
  {
    "name": "Shudesh Kumar",
    "mobile_number": "878996473.0",
    "assembly": "Tikari"
  },
  {
    "name": "Md. Tahuid",
    "mobile_number": "9431292623.0",
    "assembly": "Tikari"
  },
  {
    "name": "Ranjan Yadav",
    "mobile_number": "9006491194.0",
    "assembly": "Tikari"
  },
  {
    "name": "Dablu Kumar",
    "mobile_number": "6204192749.0",
    "assembly": "Tikari"
  },
  {
    "name": "Guddu Kumar",
    "mobile_number": "8709532549.0",
    "assembly": "Tikari"
  },
  {
    "name": "Aman Kumar",
    "mobile_number": "6203208472.0",
    "assembly": "Tikari"
  },
  {
    "name": "Aman Gupta",
    "mobile_number": "9279038472.0",
    "assembly": "Tikari"
  },
  {
    "name": "Aman Rathor",
    "mobile_number": "7667730455.0",
    "assembly": "Tikari"
  },
  {
    "name": "Rajnish Kumar",
    "mobile_number": "6203303043.0",
    "assembly": "Tikari"
  },
  {
    "name": "Chitranjan Kumar",
    "mobile_number": "6200141584.0",
    "assembly": "Tikari"
  },
  {
    "name": "Sourav Kumar",
    "mobile_number": "9241697868.0",
    "assembly": "Tikari"
  },
  {
    "name": "Randhir Kumar",
    "mobile_number": "7480929489.0",
    "assembly": "Tikari"
  },
  {
    "name": "Kush Ranjan",
    "mobile_number": "8797639217.0",
    "assembly": "Tikari"
  },
  {
    "name": "Gunjan Kumar",
    "mobile_number": "6205340964.0",
    "assembly": "Tikari"
  },
  {
    "name": "Ranjan Kumar",
    "mobile_number": "8791639217.0",
    "assembly": "Tikari"
  },
  {
    "name": "Ayush Kumar",
    "mobile_number": "9122244868.0",
    "assembly": "Tikari"
  },
  {
    "name": "Sonu Kumar",
    "mobile_number": "9693404461.0",
    "assembly": "Tikari"
  },
  {
    "name": "Rajveer Singh",
    "mobile_number": "6204731272.0",
    "assembly": "Tikari"
  },
  {
    "name": "Md. Abdul Hamir",
    "mobile_number": "7541031168.0",
    "assembly": "Tikari"
  },
  {
    "name": "Robin Sharma",
    "mobile_number": "980188133.0",
    "assembly": "Tikari"
  },
  {
    "name": "Upendra Kumar",
    "mobile_number": "9771297370.0",
    "assembly": "Tikari"
  },
  {
    "name": "Gunjan Devi",
    "mobile_number": "7766875105.0",
    "assembly": "Tikari"
  },
  {
    "name": "Akshay Choudhary",
    "mobile_number": "7488308839.0",
    "assembly": "Tikari"
  },
  {
    "name": "Md Haseeb",
    "mobile_number": "7520145681.0",
    "assembly": "Pranpur"
  },
  {
    "name": "Md Sami Akhtar",
    "mobile_number": "9939489345.0",
    "assembly": "Pranpur"
  },
  {
    "name": "Md Jahangir Alam",
    "mobile_number": "9006727605, 6206600906",
    "assembly": "Pranpur"
  },
  {
    "name": "Md Firoj",
    "mobile_number": "7260979038, 7633900190",
    "assembly": "Pranpur"
  },
  {
    "name": "Md Sajid Ali",
    "mobile_number": "7903381812.0",
    "assembly": "Pranpur"
  },
  {
    "name": "Md Tanveer Shah",
    "mobile_number": "9264167757.0",
    "assembly": "Pranpur"
  },
  {
    "name": "Md Hashim",
    "mobile_number": "9798147335.0",
    "assembly": "Pranpur"
  },
  {
    "name": "Firoz Alam",
    "mobile_number": "8873758984.0",
    "assembly": "Pranpur"
  },
  {
    "name": "Md Firoz Alam",
    "mobile_number": "9661518971.0",
    "assembly": "Pranpur"
  },
  {
    "name": "Md Anwar Alam",
    "mobile_number": "8210787306.0",
    "assembly": "Pranpur"
  },
  {
    "name": "Md Shabbir",
    "mobile_number": "7903915451.0",
    "assembly": "Pranpur"
  },
  {
    "name": "Sukhdev Rai",
    "mobile_number": "9939026809.0",
    "assembly": "Pranpur"
  },
  {
    "name": "Md Mamnoon Akhtar",
    "mobile_number": "7631212149.0",
    "assembly": "Pranpur"
  },
  {
    "name": "Mir Sultan Ahmad",
    "mobile_number": "7367838076.0",
    "assembly": "Pranpur"
  },
  {
    "name": "Md Mushfique Alam",
    "mobile_number": "9508652602.0",
    "assembly": "Pranpur"
  },
  {
    "name": "Md Shah Jahan",
    "mobile_number": "9113325794.0",
    "assembly": "Pranpur"
  },
  {
    "name": "Md Shamim Akhtar",
    "mobile_number": "8292199733.0",
    "assembly": "Pranpur"
  },
  {
    "name": "Md Azad Alam",
    "mobile_number": "9304913550.0",
    "assembly": "Pranpur"
  },
  {
    "name": "Nadim Akhtar",
    "mobile_number": "6377194795.0",
    "assembly": "Pranpur"
  },
  {
    "name": "Musarraf Reza",
    "mobile_number": "8972414640.0",
    "assembly": "Pranpur"
  },
  {
    "name": "Rinku Kumari",
    "mobile_number": "9162258006.0",
    "assembly": "Pranpur"
  },
  {
    "name": "Sunil Kumar Sorem",
    "mobile_number": "8102597758.0",
    "assembly": "Pranpur"
  },
  {
    "name": "Tufail Ali Raza",
    "mobile_number": "8368302453.0",
    "assembly": "Pranpur"
  },
  {
    "name": "Nikhil Sharma",
    "mobile_number": "7274878501.0",
    "assembly": "Pranpur"
  },
  {
    "name": "Sanjay Rai",
    "mobile_number": "6202368484.0",
    "assembly": "Pranpur"
  },
  {
    "name": "Rahil Ali Shah",
    "mobile_number": "9650501192.0",
    "assembly": "Pranpur"
  },
  {
    "name": "Saiyed Imtiyaz Ali",
    "mobile_number": "9934019475.0",
    "assembly": "Pranpur"
  },
  {
    "name": "Ram Chandra Sharma",
    "mobile_number": "9973950437.0",
    "assembly": "Pranpur"
  },
  {
    "name": "MD Sajid Alam",
    "mobile_number": "9931730841.0",
    "assembly": "Pranpur"
  },
  {
    "name": "Ranjeet Ravi Das",
    "mobile_number": "7643067272.0",
    "assembly": "Pranpur"
  },
  {
    "name": "Govind Rai",
    "mobile_number": "8252412964.0",
    "assembly": "Pranpur"
  },
  {
    "name": "Zulfiqar Ansari",
    "mobile_number": "7739916619.0",
    "assembly": "Pranpur"
  },
  {
    "name": "Dharmanand Mistry",
    "mobile_number": "9661817387, 8084037146",
    "assembly": "Pranpur"
  },
  {
    "name": "Raushan Jamil",
    "mobile_number": "7320883378.0",
    "assembly": "Pranpur"
  },
  {
    "name": "Md Nezamuddin",
    "mobile_number": "7033056676.0",
    "assembly": "Pranpur"
  },
  {
    "name": "Pawan Kumar Poddar",
    "mobile_number": "9996405211.0",
    "assembly": "Pranpur"
  },
  {
    "name": "Akhtar",
    "mobile_number": "7033013470.0",
    "assembly": "Pranpur"
  },
  {
    "name": "Md Sarfaraz",
    "mobile_number": "7543848949.0",
    "assembly": "Pranpur"
  },
  {
    "name": "Sanjay Rai",
    "mobile_number": "8092728916.0",
    "assembly": "Pranpur"
  },
  {
    "name": "Md Naushad Alam",
    "mobile_number": "9955445933.0",
    "assembly": "Pranpur"
  },
  {
    "name": "Guddu",
    "mobile_number": "7091361785.0",
    "assembly": "Pranpur"
  },
  {
    "name": "Pradip Kumar Rai",
    "mobile_number": "8084852393.0",
    "assembly": "Pranpur"
  },
  {
    "name": "Md Shadab Karim",
    "mobile_number": "7488257331.0",
    "assembly": "Pranpur"
  },
  {
    "name": "Md Akhtar",
    "mobile_number": "9304212043.0",
    "assembly": "Pranpur"
  },
  {
    "name": "Pappu Singh",
    "mobile_number": "6299737282.0",
    "assembly": "Pranpur"
  },
  {
    "name": "Md Raunak",
    "mobile_number": "8809354786.0",
    "assembly": "Pranpur"
  },
  {
    "name": "Md Sanaullah",
    "mobile_number": "7739969599.0",
    "assembly": "Pranpur"
  },
  {
    "name": "Amjad Alam",
    "mobile_number": "9430081363.0",
    "assembly": "Kishanganj"
  },
  {
    "name": "Anchan Devi",
    "mobile_number": "9608007073.0",
    "assembly": "Kishanganj"
  },
  {
    "name": "Ashfaq Alam",
    "mobile_number": "7908608094.0",
    "assembly": "Kishanganj"
  },
  {
    "name": "Badrul Alam",
    "mobile_number": "9564198822.0",
    "assembly": "Kishanganj"
  },
  {
    "name": "Budhan Singh",
    "mobile_number": "6206192169.0",
    "assembly": "Kishanganj"
  },
  {
    "name": "Farhat",
    "mobile_number": "6201816401.0",
    "assembly": "Kishanganj"
  },
  {
    "name": "Faryaz Alam",
    "mobile_number": "7667519336.0",
    "assembly": "Kishanganj"
  },
  {
    "name": "Gultaz",
    "mobile_number": "9241370743.0",
    "assembly": "Kishanganj"
  },
  {
    "name": "Jabbar",
    "mobile_number": "8521888445.0",
    "assembly": "Kishanganj"
  },
  {
    "name": "Jahangir Alam",
    "mobile_number": "9933904605.0",
    "assembly": "Kishanganj"
  },
  {
    "name": "Md Ahsan",
    "mobile_number": "9478685134.0",
    "assembly": "Kishanganj"
  },
  {
    "name": "Md Kabir",
    "mobile_number": "9113700252.0",
    "assembly": "Kishanganj"
  },
  {
    "name": "Md Rehan",
    "mobile_number": "7292830314.0",
    "assembly": "Kishanganj"
  },
  {
    "name": "Meraj Alam",
    "mobile_number": "6201981464.0",
    "assembly": "Kishanganj"
  },
  {
    "name": "Mohd Resu",
    "mobile_number": "7739320475.0",
    "assembly": "Kishanganj"
  },
  {
    "name": "Mohd Shadab",
    "mobile_number": "9234539898.0",
    "assembly": "Kishanganj"
  },
  {
    "name": "Muftadi",
    "mobile_number": "6299419122.0",
    "assembly": "Kishanganj"
  },
  {
    "name": "Radha Kumari",
    "mobile_number": "6202309302.0",
    "assembly": "Kishanganj"
  },
  {
    "name": "Rakesh Das",
    "mobile_number": "6201383079.0",
    "assembly": "Kishanganj"
  },
  {
    "name": "Sanjay",
    "mobile_number": "9631247871.0",
    "assembly": "Kishanganj"
  },
  {
    "name": "Sanjay Saini",
    "mobile_number": "8002783520.0",
    "assembly": "Kishanganj"
  },
  {
    "name": "Thabasum",
    "mobile_number": "9835962089.0",
    "assembly": "Kishanganj"
  },
  {
    "name": "Amanullah",
    "mobile_number": "9693567984.0",
    "assembly": "Kishanganj"
  },
  {
    "name": "Shabir Alam",
    "mobile_number": "6201595936.0",
    "assembly": "Kishanganj"
  },
  {
    "name": "Nayeem Aktar",
    "mobile_number": "9955090896.0",
    "assembly": "Kishanganj"
  },
  {
    "name": "Kausher Alam",
    "mobile_number": "7992376020.0",
    "assembly": "Kishanganj"
  },
  {
    "name": "Kishor Kumar",
    "mobile_number": "9142165692.0",
    "assembly": "Kishanganj"
  },
  {
    "name": "Shadab Alam",
    "mobile_number": "6204005191.0",
    "assembly": "Kishanganj"
  },
  {
    "name": "Ziauddin",
    "mobile_number": "9852787878.0",
    "assembly": "Aurangabad"
  },
  {
    "name": "Manoj",
    "mobile_number": "6203448718.0",
    "assembly": "Aurangabad"
  },
  {
    "name": "Aslam",
    "mobile_number": "9504732283.0",
    "assembly": "Aurangabad"
  },
  {
    "name": "Muneer Khan",
    "mobile_number": "9931217442.0",
    "assembly": "Aurangabad"
  },
  {
    "name": "Shahnawaz",
    "mobile_number": "7979032014.0",
    "assembly": "Aurangabad"
  },
  {
    "name": "Afzal Khan",
    "mobile_number": "9452409541.0",
    "assembly": "Aurangabad"
  },
  {
    "name": "Sushil Kumar Yadav",
    "mobile_number": "8603520234.0",
    "assembly": "Aurangabad"
  },
  {
    "name": "Nitin Kumar Yadav",
    "mobile_number": "9572842130.0",
    "assembly": "Aurangabad"
  },
  {
    "name": "Sudhir Kumar",
    "mobile_number": "9939312926.0",
    "assembly": "Aurangabad"
  },
  {
    "name": "Manish Kumar Yadav",
    "mobile_number": "9473294914.0",
    "assembly": "Aurangabad"
  },
  {
    "name": "Rodal Yadav",
    "mobile_number": "8969582082.0",
    "assembly": "Aurangabad"
  },
  {
    "name": "Chandrashekhar Kumar",
    "mobile_number": "6204785007.0",
    "assembly": "Aurangabad"
  },
  {
    "name": "Kripa Shankar",
    "mobile_number": "9241038324.0",
    "assembly": "Aurangabad"
  },
  {
    "name": "Aman Kumar",
    "mobile_number": "7780062009.0",
    "assembly": "Aurangabad"
  },
  {
    "name": "Sonu Kumar",
    "mobile_number": "7370918902.0",
    "assembly": "Aurangabad"
  },
  {
    "name": "Pradeep Kumar",
    "mobile_number": "6202140134.0",
    "assembly": "Aurangabad"
  },
  {
    "name": "Raju Kumar",
    "mobile_number": "9102927676.0",
    "assembly": "Aurangabad"
  },
  {
    "name": "Bitu Kumar",
    "mobile_number": "7667300586.0",
    "assembly": "Aurangabad"
  },
  {
    "name": "Golu Kumar",
    "mobile_number": "7050061768.0",
    "assembly": "Aurangabad"
  },
  {
    "name": "Md. Asgar",
    "mobile_number": "8777674850.0",
    "assembly": "Aurangabad"
  },
  {
    "name": "Bhola Kumar",
    "mobile_number": "6202813137.0",
    "assembly": "Aurangabad"
  },
  {
    "name": "Shah Faisal",
    "mobile_number": "7739747146.0",
    "assembly": "Aurangabad"
  },
  {
    "name": "Jaylaxman",
    "mobile_number": "8804625606.0",
    "assembly": "Aurangabad"
  },
  {
    "name": "Nandu Yadav",
    "mobile_number": "7781852439.0",
    "assembly": "Aurangabad"
  },
  {
    "name": "Imteyaz",
    "mobile_number": "8409571632.0",
    "assembly": "Aurangabad"
  },
  {
    "name": "Muneer Ahmed",
    "mobile_number": "7654395511.0",
    "assembly": "Aurangabad"
  },
  {
    "name": "Suman Yadav",
    "mobile_number": "7091591301.0",
    "assembly": "Aurangabad"
  },
  {
    "name": "Deepak Kumar Kushwaha",
    "mobile_number": "7321870273.0",
    "assembly": "Aurangabad"
  },
  {
    "name": "Deepak Kumar Thakur",
    "mobile_number": "9060333407.0",
    "assembly": "Aurangabad"
  },
  {
    "name": "Abhay Kumar Yadav",
    "mobile_number": "9304752754.0",
    "assembly": "Aurangabad"
  },
  {
    "name": "Mahfooz Alam",
    "mobile_number": "6203824909.0",
    "assembly": "Aurangabad"
  },
  {
    "name": "Md. Taha",
    "mobile_number": "9163978025.0",
    "assembly": "Aurangabad"
  },
  {
    "name": "Vishal Kumar Bittu",
    "mobile_number": "7250663100.0",
    "assembly": "Chiraya"
  },
  {
    "name": "Mohammad Sanaula",
    "mobile_number": "9771560886.0",
    "assembly": "Chiraya"
  },
  {
    "name": "Abdul Sebad Ansari",
    "mobile_number": "8521056237.0",
    "assembly": "Chiraya"
  },
  {
    "name": "Subek Kumar",
    "mobile_number": "7654756420.0",
    "assembly": "Chiraya"
  },
  {
    "name": "Rupesh Kumar",
    "mobile_number": "9708666676.0",
    "assembly": "Chiraya"
  },
  {
    "name": "Munna Yadav",
    "mobile_number": "6202641250.0",
    "assembly": "Chiraya"
  },
  {
    "name": "Pappu Yadav",
    "mobile_number": "9708577062.0",
    "assembly": "Chiraya"
  },
  {
    "name": "Arshad",
    "mobile_number": "8209823203.0",
    "assembly": "Chiraya"
  },
  {
    "name": "Md Kalim",
    "mobile_number": "9507341485.0",
    "assembly": "Chiraya"
  },
  {
    "name": "Munna Yadav",
    "mobile_number": "9113360727.0",
    "assembly": "Chiraya"
  },
  {
    "name": "Rameswar Yadav",
    "mobile_number": "9507091169.0",
    "assembly": "Chiraya"
  },
  {
    "name": "Dharmendra Kumar Singh",
    "mobile_number": "9801159370.0",
    "assembly": "Chiraya"
  },
  {
    "name": "Zalim Akhtar",
    "mobile_number": "9525297300.0",
    "assembly": "Chiraya"
  },
  {
    "name": "Asfak",
    "mobile_number": "6200434413-",
    "assembly": "Chiraya"
  },
  {
    "name": "Aditya Kumar",
    "mobile_number": "6205397411.0",
    "assembly": "Chiraya"
  },
  {
    "name": "Trisha Yadav",
    "mobile_number": "8210032428.0",
    "assembly": "Chiraya"
  },
  {
    "name": "Devbrat Kumar",
    "mobile_number": "9128145915.0",
    "assembly": "Chiraya"
  },
  {
    "name": "Arvind Jaiswal",
    "mobile_number": "7519342464.0",
    "assembly": "Chiraya"
  },
  {
    "name": "Dharmendra Yadav",
    "mobile_number": "9708665685.0",
    "assembly": "Chiraya"
  },
  {
    "name": "Abhishek Yadav",
    "mobile_number": "9798072478.0",
    "assembly": "Chiraya"
  },
  {
    "name": "Ravi Kumar",
    "mobile_number": "9576520293.0",
    "assembly": "Chiraya"
  },
  {
    "name": "Pramod Yadav",
    "mobile_number": "9525209030.0",
    "assembly": "Chiraya"
  },
  {
    "name": "Mohammad Amantula",
    "mobile_number": "9110989115.0",
    "assembly": "Chiraya"
  },
  {
    "name": "Sajid Iqbal",
    "mobile_number": "8310770141.0",
    "assembly": "Chiraya"
  },
  {
    "name": "Nilesh Yadav",
    "mobile_number": "8235783797.0",
    "assembly": "Chiraya"
  },
  {
    "name": "Firoz Alam",
    "mobile_number": "9560602801.0",
    "assembly": "Chiraya"
  },
  {
    "name": "Vinod Yadav",
    "mobile_number": "6201273446.0",
    "assembly": "Chiraya"
  },
  {
    "name": "Snehlata Devi",
    "mobile_number": "7250067597.0",
    "assembly": "Kahalgaon"
  },
  {
    "name": "Tarkeshwar Prasad",
    "mobile_number": "7782031609.0",
    "assembly": "Kahalgaon"
  },
  {
    "name": "Mamta Kumari",
    "mobile_number": "7631687849.0",
    "assembly": "Kahalgaon"
  },
  {
    "name": "Shekhar Suman",
    "mobile_number": "9122036200.0",
    "assembly": "Kahalgaon"
  },
  {
    "name": "Pappu",
    "mobile_number": "8877843337.0",
    "assembly": "Kahalgaon"
  },
  {
    "name": "Azad Rajak",
    "mobile_number": "9523837176.0",
    "assembly": "Kahalgaon"
  },
  {
    "name": "Rajiv Ranjan",
    "mobile_number": "9162375949.0",
    "assembly": "Kahalgaon"
  },
  {
    "name": "Satyam Kumar",
    "mobile_number": "7258810506.0",
    "assembly": "Kahalgaon"
  },
  {
    "name": "Sublesh Yadav",
    "mobile_number": "8969428464.0",
    "assembly": "Kahalgaon"
  },
  {
    "name": "Nityanand",
    "mobile_number": "9973080570.0",
    "assembly": "Kahalgaon"
  },
  {
    "name": "Mukesh Paswan",
    "mobile_number": "7870161800.0",
    "assembly": "Kahalgaon"
  },
  {
    "name": "Raju Ranjana",
    "mobile_number": "6201361489.0",
    "assembly": "Kahalgaon"
  },
  {
    "name": "Banti Kumar",
    "mobile_number": "9162880879.0",
    "assembly": "Kahalgaon"
  },
  {
    "name": "Sangita Kumari",
    "mobile_number": "9693680804.0",
    "assembly": "Kahalgaon"
  },
  {
    "name": "Jaya Priti",
    "mobile_number": "7542002246.0",
    "assembly": "Kahalgaon"
  },
  {
    "name": "Shaligram",
    "mobile_number": "9771139826.0",
    "assembly": "Kahalgaon"
  },
  {
    "name": "Badal Kumar",
    "mobile_number": "8340645622.0",
    "assembly": "Kahalgaon"
  },
  {
    "name": "Shubham Kumar",
    "mobile_number": "9123447073.0",
    "assembly": "Kahalgaon"
  },
  {
    "name": "Chhotu Kumar",
    "mobile_number": "7488901148.0",
    "assembly": "Kahalgaon"
  },
  {
    "name": "Sulekha Bharti",
    "mobile_number": "9934813501.0",
    "assembly": "Kahalgaon"
  },
  {
    "name": "Vishnu Kumar",
    "mobile_number": "7667144607.0",
    "assembly": "Kahalgaon"
  },
  {
    "name": "Bhopal Yadav",
    "mobile_number": "7739679907.0",
    "assembly": "Kahalgaon"
  },
  {
    "name": "Saurabh Kumar",
    "mobile_number": "9304298942.0",
    "assembly": "Kahalgaon"
  },
  {
    "name": "Bhavesh Kumar",
    "mobile_number": "9905470638.0",
    "assembly": "Kahalgaon"
  },
  {
    "name": "Vikash Kumar",
    "mobile_number": "7762822074.0",
    "assembly": "Kahalgaon"
  },
  {
    "name": "Deepak Kumar",
    "mobile_number": "6204145586.0",
    "assembly": "Kahalgaon"
  },
  {
    "name": "Pritam Kumar",
    "mobile_number": "8294364226.0",
    "assembly": "Kahalgaon"
  },
  {
    "name": "Anuj Kumar",
    "mobile_number": "7050666705.0",
    "assembly": "Kahalgaon"
  },
  {
    "name": "Rajesh Ranjan",
    "mobile_number": "6206658148.0",
    "assembly": "Kahalgaon"
  },
  {
    "name": "Rajendra Prasad Yadav",
    "mobile_number": "9771145018.0",
    "assembly": "Kahalgaon"
  },
  {
    "name": "Gurudev K. Mandal",
    "mobile_number": "9162937438.0",
    "assembly": "Kahalgaon"
  },
  {
    "name": "Pankaj Kumar",
    "mobile_number": "9110956925.0",
    "assembly": "Kahalgaon"
  },
  {
    "name": "Md. Rahtaz",
    "mobile_number": "7654886047.0",
    "assembly": "Kahalgaon"
  },
  {
    "name": "Shahdev Mandal",
    "mobile_number": "8676019903.0",
    "assembly": "Kahalgaon"
  },
  {
    "name": "Sagar Kumar",
    "mobile_number": "9031965995.0",
    "assembly": "Kahalgaon"
  },
  {
    "name": "Yudhishthir Kumar",
    "mobile_number": "7520154067.0",
    "assembly": "Kahalgaon"
  },
  {
    "name": "Pawan Kishku",
    "mobile_number": "9065032392.0",
    "assembly": "Kahalgaon"
  },
  {
    "name": "Shivbalak",
    "mobile_number": "8809301200.0",
    "assembly": "Kahalgaon"
  },
  {
    "name": "Vijay Kumar",
    "mobile_number": "7766834560.0",
    "assembly": "Kahalgaon"
  },
  {
    "name": "Avinash Kumar",
    "mobile_number": "8521710511.0",
    "assembly": "Kahalgaon"
  },
  {
    "name": "Amnish Kumar",
    "mobile_number": "9155238041.0",
    "assembly": "Kahalgaon"
  },
  {
    "name": "Kartik Kumar",
    "mobile_number": "9135784710.0",
    "assembly": "Kahalgaon"
  },
  {
    "name": "Pawan Kumar",
    "mobile_number": "8298545911.0",
    "assembly": "Kahalgaon"
  },
  {
    "name": "Sanjay Kishku",
    "mobile_number": "9065032392.0",
    "assembly": "Kahalgaon"
  },
  {
    "name": "Adarsh Ankur",
    "mobile_number": "9298014227.0",
    "assembly": "Kahalgaon"
  },
  {
    "name": "Adarsh Raunak",
    "mobile_number": "7372872439.0",
    "assembly": "Kahalgaon"
  },
  {
    "name": "Dulari Devi",
    "mobile_number": "6200375751.0",
    "assembly": "Kahalgaon"
  },
  {
    "name": "Kanhaiya Kumar",
    "mobile_number": "8521201092.0",
    "assembly": "Kahalgaon"
  },
  {
    "name": "Rishi Kumar",
    "mobile_number": "8084565771.0",
    "assembly": "Kahalgaon"
  },
  {
    "name": "Jairam Shah",
    "mobile_number": "9555937428.0",
    "assembly": "Kahalgaon"
  },
  {
    "name": "Lalan Kumar",
    "mobile_number": "9135066161.0",
    "assembly": "Kahalgaon"
  },
  {
    "name": "Aadarsh Ankur",
    "mobile_number": "8298014227.0",
    "assembly": "Kahalgaon"
  },
  {
    "name": "Ayush Kumar",
    "mobile_number": "7643053695.0",
    "assembly": "Kahalgaon"
  },
  {
    "name": "Sanjay Kishku",
    "mobile_number": "9065032392.0",
    "assembly": "Kahalgaon"
  },
  {
    "name": "Md. Rahtaz",
    "mobile_number": "7654886047.0",
    "assembly": "Kahalgaon"
  },
  {
    "name": "Mandhat",
    "mobile_number": "7670713702.0",
    "assembly": "Kahalgaon"
  },
  {
    "name": "Ranjit Das",
    "mobile_number": "8676923016.0",
    "assembly": "Kahalgaon"
  },
  {
    "name": "Susil Kumar",
    "mobile_number": "9608143848.0",
    "assembly": "Kahalgaon"
  },
  {
    "name": "Nijamuddin Alam",
    "mobile_number": "8651505002.0",
    "assembly": "Paro"
  },
  {
    "name": "Basiruddin Alam",
    "mobile_number": "7369075500.0",
    "assembly": "Paro"
  },
  {
    "name": "Raza Ansari",
    "mobile_number": "9117343385.0",
    "assembly": "Paro"
  },
  {
    "name": "Md Irshad",
    "mobile_number": "9162641006.0",
    "assembly": "Paro"
  },
  {
    "name": "Ajay Kumar",
    "mobile_number": "6202721054.0",
    "assembly": "Paro"
  },
  {
    "name": "Md Mumtaj",
    "mobile_number": "9931083299.0",
    "assembly": "Paro"
  },
  {
    "name": "Noor Alam",
    "mobile_number": "7002464047.0",
    "assembly": "Paro"
  },
  {
    "name": "Md Faizuddin",
    "mobile_number": "9955438136.0",
    "assembly": "Paro"
  },
  {
    "name": "Jahid Alam",
    "mobile_number": "6204151263.0",
    "assembly": "Paro"
  },
  {
    "name": "Md Ansar",
    "mobile_number": "9064978953.0",
    "assembly": "Paro"
  },
  {
    "name": "Niranjan Yadav",
    "mobile_number": "9576776815.0",
    "assembly": "Paro"
  },
  {
    "name": "Inderjeet Kumar",
    "mobile_number": "8084104962.0",
    "assembly": "Paro"
  },
  {
    "name": "Vinay Yadav",
    "mobile_number": "9576772011.0",
    "assembly": "Paro"
  },
  {
    "name": "Mandipa Yadav",
    "mobile_number": "9905877730.0",
    "assembly": "Paro"
  },
  {
    "name": "Md Majuddin",
    "mobile_number": "9304610587.0",
    "assembly": "Paro"
  },
  {
    "name": "Saroj Kumar Kushwaha",
    "mobile_number": "8292597165.0",
    "assembly": "Paro"
  },
  {
    "name": "Dhiraj Kumar",
    "mobile_number": "9102837613.0",
    "assembly": "Paro"
  },
  {
    "name": "Ajay Thakur",
    "mobile_number": "8119819835.0",
    "assembly": "Paro"
  },
  {
    "name": "Pramod Kumar",
    "mobile_number": "8541852045.0",
    "assembly": "Paro"
  },
  {
    "name": "Ranjeet Kumar",
    "mobile_number": "7461046530.0",
    "assembly": "Paro"
  },
  {
    "name": "Vicky Kumar",
    "mobile_number": "8002589899.0",
    "assembly": "Paro"
  },
  {
    "name": "Nirbhay Kumar",
    "mobile_number": "7255065738.0",
    "assembly": "Paro"
  },
  {
    "name": "RAJKUMAR PANDIT",
    "mobile_number": "9934570894.0",
    "assembly": "Jale"
  },
  {
    "name": "SUJIT THAKUR",
    "mobile_number": "9973612451.0",
    "assembly": "Jale"
  },
  {
    "name": "NAGESHWAR MUKHIYA",
    "mobile_number": "9135179842.0",
    "assembly": "Jale"
  },
  {
    "name": "AQUIL SIDIQUE",
    "mobile_number": "9525434364.0",
    "assembly": "Jale"
  },
  {
    "name": "MD KHALIL AHMED",
    "mobile_number": "8961723315.0",
    "assembly": "Jale"
  },
  {
    "name": "LALIT YADAV",
    "mobile_number": "9661908833.0",
    "assembly": "Jale"
  },
  {
    "name": "MOHAMMAD KHURSHID",
    "mobile_number": "8969921695.0",
    "assembly": "Jale"
  },
  {
    "name": "GAUJAN CHOUDHARY",
    "mobile_number": "9110968636.0",
    "assembly": "Jale"
  },
  {
    "name": "PUNIYA NAND MISHR",
    "mobile_number": "9525671410.0",
    "assembly": "Jale"
  },
  {
    "name": "GAURI SHANKAR JHA",
    "mobile_number": "9771384810.0",
    "assembly": "Jale"
  },
  {
    "name": "MURARI JHA",
    "mobile_number": "8210910120.0",
    "assembly": "Jale"
  },
  {
    "name": "LOHA SINGH YADAV",
    "mobile_number": "9868590868.0",
    "assembly": "Jale"
  },
  {
    "name": "SAIFUR RAHMAN",
    "mobile_number": "6204024242.0",
    "assembly": "Jale"
  },
  {
    "name": "RAM KRISHNA RAM",
    "mobile_number": "6203494800.0",
    "assembly": "Jale"
  },
  {
    "name": "HARIWANSH DAS",
    "mobile_number": "9470437262.0",
    "assembly": "Jale"
  },
  {
    "name": "MOHAMMAD ALAUDDIN",
    "mobile_number": "8540907003.0",
    "assembly": "Jale"
  },
  {
    "name": "ABDUL QUAIYUM",
    "mobile_number": "7764892986.0",
    "assembly": "Jale"
  },
  {
    "name": "HARDIK KUMAR RAM",
    "mobile_number": "8298707748.0",
    "assembly": "Jale"
  },
  {
    "name": "SUBODH SADA MAJHI",
    "mobile_number": "8651610545.0",
    "assembly": "Jale"
  },
  {
    "name": "JAI MAJHI",
    "mobile_number": "7764876875.0",
    "assembly": "Jale"
  },
  {
    "name": "RAMASISH SADA",
    "mobile_number": "7050395922.0",
    "assembly": "Jale"
  },
  {
    "name": "RANJIT KUMAR YADAV",
    "mobile_number": "8863065154.0",
    "assembly": "Jale"
  },
  {
    "name": "RAJENDRA PASWAN",
    "mobile_number": "9330539914.0",
    "assembly": "Jale"
  },
  {
    "name": "SUNIL RAM",
    "mobile_number": "8825396071.0",
    "assembly": "Jale"
  },
  {
    "name": "RAJKISHORE RAM",
    "mobile_number": "6205955063.0",
    "assembly": "Jale"
  },
  {
    "name": "MD QAMRE ALAM",
    "mobile_number": "8797454005.0",
    "assembly": "Jale"
  },
  {
    "name": "HARIWANSH DAS",
    "mobile_number": "9334395087.0",
    "assembly": "Jale"
  },
  {
    "name": "AVDESH KUMAR MANDAL",
    "mobile_number": "9650598661.0",
    "assembly": "Jale"
  },
  {
    "name": "DR SHIWALAI YADAV",
    "mobile_number": "8521802196.0",
    "assembly": "Jale"
  },
  {
    "name": "CHAND ALAM",
    "mobile_number": "9905689456.0",
    "assembly": "Jale"
  },
  {
    "name": "NAHID MUSHTAQUE",
    "mobile_number": "9934915901.0",
    "assembly": "Jale"
  },
  {
    "name": "RAMESH KUMAR",
    "mobile_number": "9341414434.0",
    "assembly": "Jale"
  },
  {
    "name": "BUDHU MAJHI",
    "mobile_number": "9155673614.0",
    "assembly": "Jale"
  },
  {
    "name": "RAHMAT ALI",
    "mobile_number": "9015477132.0",
    "assembly": "Jale"
  },
  {
    "name": "JAMAL MIRZA BEG",
    "mobile_number": "9264409831.0",
    "assembly": "Jale"
  },
  {
    "name": "SUSHIL RAM",
    "mobile_number": "6201433369.0",
    "assembly": "Jale"
  },
  {
    "name": "BHUSHAN KUMAR SINGH",
    "mobile_number": "8383866929.0",
    "assembly": "Jale"
  },
  {
    "name": "PRAVEEN KUMAR",
    "mobile_number": "9576711207.0",
    "assembly": "Jale"
  },
  {
    "name": "NIRANJAN KUMAR",
    "mobile_number": "9122028683.0",
    "assembly": "Jale"
  },
  {
    "name": "NALBUNI YADAV",
    "mobile_number": "9931249517.0",
    "assembly": "Jale"
  },
  {
    "name": "RAMDAHIN RAI",
    "mobile_number": "7654419406.0",
    "assembly": "Jale"
  },
  {
    "name": "JHAKRA PASWAN",
    "mobile_number": "9661952426.0",
    "assembly": "Jale"
  },
  {
    "name": "EHSANUL HAQUE",
    "mobile_number": "6207654476.0",
    "assembly": "Jale"
  },
  {
    "name": "KANHAIYA PRASAD",
    "mobile_number": "8102088233.0",
    "assembly": "Jale"
  },
  {
    "name": "Mohammad Kalimullah (Kalim Bhai)",
    "mobile_number": "7070520956.0",
    "assembly": "Gopalganj"
  },
  {
    "name": "Anita Tiwari",
    "mobile_number": "8828075239.0",
    "assembly": "Gopalganj"
  },
  {
    "name": "Pankaj Shrivastav",
    "mobile_number": "7970485898.0",
    "assembly": "Gopalganj"
  },
  {
    "name": "Qaumudin",
    "mobile_number": "9801298771.0",
    "assembly": "Gopalganj"
  },
  {
    "name": "Sameer Ansari",
    "mobile_number": "6201226233.0",
    "assembly": "Gopalganj"
  },
  {
    "name": "Irshad Ansari",
    "mobile_number": "6299424250.0",
    "assembly": "Gopalganj"
  },
  {
    "name": "Manjeet Yadav",
    "mobile_number": "7004567973.0",
    "assembly": "Gopalganj"
  },
  {
    "name": "Dharmendra Kumar",
    "mobile_number": "9110185905.0",
    "assembly": "Gopalganj"
  },
  {
    "name": "Abdul Ansari",
    "mobile_number": "9955332296.0",
    "assembly": "Gopalganj"
  },
  {
    "name": "Nilu Kumari Yadav",
    "mobile_number": "7541864152.0",
    "assembly": "Gopalganj"
  },
  {
    "name": "Faim Akhtar",
    "mobile_number": "7250748770.0",
    "assembly": "Gopalganj"
  },
  {
    "name": "Sanjay Ram",
    "mobile_number": "8757904358.0",
    "assembly": "Gopalganj"
  },
  {
    "name": "Avdesh Ram",
    "mobile_number": "9128325958.0",
    "assembly": "Gopalganj"
  },
  {
    "name": "Mir Hasan Ansari",
    "mobile_number": "7292840205.0",
    "assembly": "Gopalganj"
  },
  {
    "name": "Ramakant Mukhiya",
    "mobile_number": "7781044868.0",
    "assembly": "Gopalganj"
  },
  {
    "name": "Rambabu Mahto",
    "mobile_number": "8969253849.0",
    "assembly": "Gopalganj"
  },
  {
    "name": "Jitendra Prasad",
    "mobile_number": "9103990159.0",
    "assembly": "Gopalganj"
  },
  {
    "name": "Chancee Yadav",
    "mobile_number": "8804210544.0",
    "assembly": "Gopalganj"
  },
  {
    "name": "Tarkeshwar Kumar",
    "mobile_number": "9934256300.0",
    "assembly": "Gopalganj"
  },
  {
    "name": "Washim Akram",
    "mobile_number": "9534696050.0",
    "assembly": "Gopalganj"
  },
  {
    "name": "Kalamudin Alam",
    "mobile_number": "9792522955.0",
    "assembly": "Gopalganj"
  },
  {
    "name": "Uma Shankar Roy",
    "mobile_number": "9507689463.0",
    "assembly": "Rosera"
  },
  {
    "name": "Sunil Kumar",
    "mobile_number": "8434416844.0",
    "assembly": "Rosera"
  },
  {
    "name": "Subodh Kumar",
    "mobile_number": "9525643915.0",
    "assembly": "Rosera"
  },
  {
    "name": "Mukesh Kumar",
    "mobile_number": "8051281222.0",
    "assembly": "Rosera"
  },
  {
    "name": "Bipin Kumar",
    "mobile_number": "7370981710.0",
    "assembly": "Rosera"
  },
  {
    "name": "Rishu Raman",
    "mobile_number": "8298316114.0",
    "assembly": "Rosera"
  },
  {
    "name": "Sunil Kumar",
    "mobile_number": "9525930962.0",
    "assembly": "Rosera"
  },
  {
    "name": "Chandan Kumar",
    "mobile_number": "8877335426.0",
    "assembly": "Rosera"
  },
  {
    "name": "Rajan Kumar",
    "mobile_number": "9931256983.0",
    "assembly": "Rosera"
  },
  {
    "name": "Bhukhli Devi",
    "mobile_number": "7367934354.0",
    "assembly": "Rosera"
  },
  {
    "name": "Vinod Yadav",
    "mobile_number": "9006220735.0",
    "assembly": "Rosera"
  },
  {
    "name": "Kirtan Rajak",
    "mobile_number": "9741143274.0",
    "assembly": "Rosera"
  },
  {
    "name": "Raj Kumar Das",
    "mobile_number": "7011766399.0",
    "assembly": "Rosera"
  },
  {
    "name": "Sarita Devi",
    "mobile_number": "",
    "assembly": "Rosera"
  },
  {
    "name": "Sunil Kumar",
    "mobile_number": "7988976975.0",
    "assembly": "Rosera"
  },
  {
    "name": "Manoj Kumar",
    "mobile_number": "9525642852.0",
    "assembly": "Rosera"
  },
  {
    "name": "Rajesh Roy",
    "mobile_number": "7431922495.0",
    "assembly": "Rosera"
  },
  {
    "name": "Pankaj Das",
    "mobile_number": "6287334301.0",
    "assembly": "Rosera"
  },
  {
    "name": "Raju Rajak",
    "mobile_number": "9113570636.0",
    "assembly": "Rosera"
  },
  {
    "name": "Raj Kumar yadav",
    "mobile_number": "8217360257.0",
    "assembly": "Rosera"
  },
  {
    "name": "Ram Shankar yadav",
    "mobile_number": "9328409612.0",
    "assembly": "Rosera"
  },
  {
    "name": "Tuntun Prasad",
    "mobile_number": "8809723577.0",
    "assembly": "Rosera"
  },
  {
    "name": "Shil Kumar Roy",
    "mobile_number": "9931688723.0",
    "assembly": "Rosera"
  },
  {
    "name": "Vikash Kumar",
    "mobile_number": "7549354468.0",
    "assembly": "Rosera"
  },
  {
    "name": "Anguri Praveen",
    "mobile_number": "9279115161.0",
    "assembly": "Rosera"
  },
  {
    "name": "Supanjan Kumar",
    "mobile_number": "8581921550.0",
    "assembly": "Rosera"
  },
  {
    "name": "Ravish Kumar",
    "mobile_number": "9294998500.0",
    "assembly": "Rosera"
  },
  {
    "name": "Nitish Kumar",
    "mobile_number": "9135100301.0",
    "assembly": "Rosera"
  },
  {
    "name": "Praveen",
    "mobile_number": "9570553836.0",
    "assembly": "Rosera"
  },
  {
    "name": "Chandrasekhar",
    "mobile_number": "7654176258.0",
    "assembly": "Rosera"
  },
  {
    "name": "Ikalq",
    "mobile_number": "9576419133.0",
    "assembly": "Rosera"
  },
  {
    "name": "Meraj Khan",
    "mobile_number": "8919244660.0",
    "assembly": "Rosera"
  },
  {
    "name": "Seraj Khan",
    "mobile_number": "7808552461.0",
    "assembly": "Rosera"
  },
  {
    "name": "Rohit Kumar",
    "mobile_number": "7491049631.0",
    "assembly": "Rosera"
  },
  {
    "name": "Shankar Sahni",
    "mobile_number": "",
    "assembly": "Rosera"
  },
  {
    "name": "Ranjit Sahni",
    "mobile_number": "7809496240.0",
    "assembly": "Rosera"
  },
  {
    "name": "Asha Devi",
    "mobile_number": "",
    "assembly": "Rosera"
  },
  {
    "name": "Ram Dulari Devi",
    "mobile_number": "",
    "assembly": "Rosera"
  },
  {
    "name": "Md Wasim",
    "mobile_number": "7491938414.0",
    "assembly": "Rosera"
  },
  {
    "name": "Rama Devi",
    "mobile_number": "8809443580.0",
    "assembly": "Rosera"
  },
  {
    "name": "Ashok Yadav",
    "mobile_number": "7369038675.0",
    "assembly": "Rosera"
  },
  {
    "name": "Manoj Kumar",
    "mobile_number": "8709443505.0",
    "assembly": "Rosera"
  },
  {
    "name": "Arun Yadav",
    "mobile_number": "",
    "assembly": "Rosera"
  },
  {
    "name": "Mukesh Punjabi",
    "mobile_number": "6201760288.0",
    "assembly": "Rosera"
  },
  {
    "name": "Dileep Yadav",
    "mobile_number": "",
    "assembly": "Rosera"
  },
  {
    "name": "Anjali Kumari",
    "mobile_number": "6208773351.0",
    "assembly": "Rosera"
  },
  {
    "name": "Sanju Kumar",
    "mobile_number": "6202824718.0",
    "assembly": "Rosera"
  },
  {
    "name": "Umesh Kumar",
    "mobile_number": "7488727175.0",
    "assembly": "Rajgir"
  },
  {
    "name": "Prem Raj",
    "mobile_number": "8809630892.0",
    "assembly": "Rajgir"
  },
  {
    "name": "Sonu Kumar",
    "mobile_number": "7488513884.0",
    "assembly": "Rajgir"
  },
  {
    "name": "Mohan Kumar Yadav",
    "mobile_number": "8409826137.0",
    "assembly": "Rajgir"
  },
  {
    "name": "Subhash Kumar",
    "mobile_number": "9006234655.0",
    "assembly": "Rajgir"
  },
  {
    "name": "Anil yadav",
    "mobile_number": "7091923787.0",
    "assembly": "Rajgir"
  },
  {
    "name": "Subhash Kumar",
    "mobile_number": "8124714610.0",
    "assembly": "Rajgir"
  },
  {
    "name": "Lalan Paswan",
    "mobile_number": "7004525480.0",
    "assembly": "Rajgir"
  },
  {
    "name": "Bijendar Yadav",
    "mobile_number": "9835497527.0",
    "assembly": "Rajgir"
  },
  {
    "name": "Md Sufan Ansari",
    "mobile_number": "8271750772.0",
    "assembly": "Rajgir"
  },
  {
    "name": "Shahnawaz Alam",
    "mobile_number": "8409777247.0",
    "assembly": "Rajgir"
  },
  {
    "name": "Ravish Kumar",
    "mobile_number": "9199348446.0",
    "assembly": "Rajgir"
  },
  {
    "name": "Satyendar Prasad",
    "mobile_number": "7549393163.0",
    "assembly": "Rajgir"
  },
  {
    "name": "Raja Babu",
    "mobile_number": "8862814222.0",
    "assembly": "Rajgir"
  },
  {
    "name": "Prahlad Kumar",
    "mobile_number": "7903398470.0",
    "assembly": "Rajgir"
  },
  {
    "name": "Vinod Yadav",
    "mobile_number": "8340739610.0",
    "assembly": "Rajgir"
  },
  {
    "name": "Pintu Kumar",
    "mobile_number": "7992242754.0",
    "assembly": "Rajgir"
  },
  {
    "name": "Vikas Kumar Chaudhary",
    "mobile_number": "9766331850.0",
    "assembly": "Rajgir"
  },
  {
    "name": "Mukesh Paswan",
    "mobile_number": "6205372009.0",
    "assembly": "Rajgir"
  },
  {
    "name": "Sandeep Kumar",
    "mobile_number": "6201785701.0",
    "assembly": "Rajgir"
  },
  {
    "name": "Pappu Kumar",
    "mobile_number": "9608863550.0",
    "assembly": "Rajgir"
  },
  {
    "name": "Prahlad Yadav",
    "mobile_number": "9128468615.0",
    "assembly": "Rajgir"
  },
  {
    "name": "Veer Bahadur Manjhi",
    "mobile_number": "7320820657.0",
    "assembly": "Rajgir"
  },
  {
    "name": "Santosh Kumar",
    "mobile_number": "7979077358.0",
    "assembly": "Rajgir"
  },
  {
    "name": "Pappu Kumar Yadav",
    "mobile_number": "6203748494.0",
    "assembly": "Rajgir"
  },
  {
    "name": "Sanjay Prasad",
    "mobile_number": "6206650407.0",
    "assembly": "Rajgir"
  },
  {
    "name": "Bablu Kumar Sharma",
    "mobile_number": "7322942937.0",
    "assembly": "Rajgir"
  },
  {
    "name": "Faizan Khan",
    "mobile_number": "7294022932.0",
    "assembly": "Rajgir"
  },
  {
    "name": "Raja Babu",
    "mobile_number": "6201630344.0",
    "assembly": "Rajgir"
  },
  {
    "name": "Amit Kumar",
    "mobile_number": "9122256623.0",
    "assembly": "Rajgir"
  },
  {
    "name": "Barti Devi",
    "mobile_number": "9572808661.0",
    "assembly": "Rajgir"
  },
  {
    "name": "Farhan Khan",
    "mobile_number": "8603739297.0",
    "assembly": "Rajgir"
  },
  {
    "name": "Anuj Kumar",
    "mobile_number": "8226834984.0",
    "assembly": "Rajgir"
  },
  {
    "name": "Mohit Kumar",
    "mobile_number": "6203886623.0",
    "assembly": "Rajgir"
  },
  {
    "name": "Raja Babu",
    "mobile_number": "6204862100.0",
    "assembly": "Rajgir"
  },
  {
    "name": "Parmod Kumar",
    "mobile_number": "9304402581.0",
    "assembly": "Rajgir"
  },
  {
    "name": "Bihari Manjhi",
    "mobile_number": "6299849892.0",
    "assembly": "Rajgir"
  },
  {
    "name": "Abhayjeet Kumar",
    "mobile_number": "8294986386.0",
    "assembly": "Rajgir"
  },
  {
    "name": "Amit Kumar",
    "mobile_number": "9033161595.0",
    "assembly": "Rajgir"
  },
  {
    "name": "Danish Khan",
    "mobile_number": "9905115387.0",
    "assembly": "Rajgir"
  },
  {
    "name": "Gulshan Kumar",
    "mobile_number": "8862826474.0",
    "assembly": "Rajgir"
  },
  {
    "name": "Hari Om",
    "mobile_number": "7667723682.0",
    "assembly": "Rajgir"
  }
]